haystack_integrations/components/retrievers/py.typed
haystack_integrations/components/retrievers/opensearch/__init__.py
haystack_integrations/components/retrievers/opensearch/bm25_retriever.py
haystack_integrations/components/retrievers/opensearch/embedding_retriever.py
haystack_integrations/components/retrievers/opensearch/metadata_retriever.py
haystack_integrations/components/retrievers/opensearch/open_search_hybrid_retriever.py
haystack_integrations/components/retrievers/opensearch/sql_retriever.py
haystack_integrations/document_stores/py.typed
haystack_integrations/document_stores/opensearch/__init__.py
haystack_integrations/document_stores/opensearch/auth.py
haystack_integrations/document_stores/opensearch/document_store.py
haystack_integrations/document_stores/opensearch/filters.py
haystack_integrations/document_stores/opensearch/opensearch_scripts.py
opensearch_haystack-6.3.0.dist-info/METADATA
opensearch_haystack-6.3.0.dist-info/WHEEL
opensearch_haystack-6.3.0.dist-info/licenses/LICENSE
opensearch_haystack-6.3.0.dist-info/RECORD
